pyppl_require.py
pyppl_require-0.0.5.dist-info/entry_points.txt
pyppl_require-0.0.5.dist-info/LICENSE
pyppl_require-0.0.5.dist-info/WHEEL
pyppl_require-0.0.5.dist-info/METADATA
pyppl_require-0.0.5.dist-info/RECORD
